patex/__init__.py
patex/patex.py
patex-0.0.1.dist-info/METADATA
patex-0.0.1.dist-info/WHEEL
patex-0.0.1.dist-info/top_level.txt
patex-0.0.1.dist-info/RECORD
