Metadata-Version: 2.1
Name: patex
Version: 0.0.1
Summary: Pattern expression
Author: Aidin T.
Author-email: at.aidin@gmail.com
Keywords: python,first package
Classifier: Development Status :: 3 - Alpha
Classifier: Intended Audience :: Education
Classifier: Programming Language :: Python :: 2
Classifier: Programming Language :: Python :: 3
Classifier: Operating System :: MacOS :: MacOS X
Classifier: Operating System :: Microsoft :: Windows
